<?xml version="1.0" encoding="UTF-8"?>
<MetaDataObject xmlns="http://v8.1c.ru/8.3/MDClasses" xmlns:app="http://v8.1c.ru/8.2/managed-application/core" xmlns:cfg="http://v8.1c.ru/8.1/data/enterprise/current-config" xmlns:cmi="http://v8.1c.ru/8.2/managed-application/cmi" xmlns:ent="http://v8.1c.ru/8.1/data/enterprise" xmlns:lf="http://v8.1c.ru/8.2/managed-application/logform" xmlns:style="http://v8.1c.ru/8.1/data/ui/style" xmlns:sys="http://v8.1c.ru/8.1/data/ui/fonts/system" xmlns:v8="http://v8.1c.ru/8.1/data/core" xmlns:v8ui="http://v8.1c.ru/8.1/data/ui" xmlns:web="http://v8.1c.ru/8.1/data/ui/colors/web" xmlns:win="http://v8.1c.ru/8.1/data/ui/colors/windows" xmlns:xen="http://v8.1c.ru/8.3/xcf/enums" xmlns:xpr="http://v8.1c.ru/8.3/xcf/predef" xmlns:xr="http://v8.1c.ru/8.3/xcf/readable" xmlns:xs="http://www.w3.org/2001/XMLSchema" xmlns:xsi="http://www.w3.org/2001/XMLSchema-instance" version="2.10">
	<Constant uuid="e602a6ad-2bec-427a-98e1-72e35e194739">
		<InternalInfo>
			<xr:GeneratedType name="ConstantManager.ГИГ_СрокАктуальностиОстатковПоставщика" category="Manager">
				<xr:TypeId>07f5f260-931d-4249-8ebc-626c68a137b0</xr:TypeId>
				<xr:ValueId>047d6bd3-47fc-4f34-a08b-b19998e3f19b</xr:ValueId>
			</xr:GeneratedType>
			<xr:GeneratedType name="ConstantValueManager.ГИГ_СрокАктуальностиОстатковПоставщика" category="ValueManager">
				<xr:TypeId>b6acb932-e5b6-4f9b-82d9-f434a1f817ad</xr:TypeId>
				<xr:ValueId>1a184826-5ad5-443c-982d-081aede72178</xr:ValueId>
			</xr:GeneratedType>
			<xr:GeneratedType name="ConstantValueKey.ГИГ_СрокАктуальностиОстатковПоставщика" category="ValueKey">
				<xr:TypeId>ba2b53d9-f7c2-4cbc-be12-1396be998d6e</xr:TypeId>
				<xr:ValueId>04a94239-d7fc-41a4-b4ce-74d274584b06</xr:ValueId>
			</xr:GeneratedType>
		</InternalInfo>
		<Properties>
			<Name>ГИГ_СрокАктуальностиОстатковПоставщика</Name>
			<Comment/>
			<ObjectBelonging>Adopted</ObjectBelonging>
			<ExtendedConfigurationObject>498e3559-ad4e-42f3-baf0-674e9c3edcc6</ExtendedConfigurationObject>
			<Type>
				<v8:Type>xs:decimal</v8:Type>
				<v8:NumberQualifiers>
					<v8:Digits>10</v8:Digits>
					<v8:FractionDigits>0</v8:FractionDigits>
					<v8:AllowedSign>Nonnegative</v8:AllowedSign>
				</v8:NumberQualifiers>
			</Type>
		</Properties>
	</Constant>
</MetaDataObject>