<?xml version="1.0" encoding="UTF-8"?>
<MetaDataObject xmlns="http://v8.1c.ru/8.3/MDClasses" xmlns:app="http://v8.1c.ru/8.2/managed-application/core" xmlns:cfg="http://v8.1c.ru/8.1/data/enterprise/current-config" xmlns:cmi="http://v8.1c.ru/8.2/managed-application/cmi" xmlns:ent="http://v8.1c.ru/8.1/data/enterprise" xmlns:lf="http://v8.1c.ru/8.2/managed-application/logform" xmlns:style="http://v8.1c.ru/8.1/data/ui/style" xmlns:sys="http://v8.1c.ru/8.1/data/ui/fonts/system" xmlns:v8="http://v8.1c.ru/8.1/data/core" xmlns:v8ui="http://v8.1c.ru/8.1/data/ui" xmlns:web="http://v8.1c.ru/8.1/data/ui/colors/web" xmlns:win="http://v8.1c.ru/8.1/data/ui/colors/windows" xmlns:xen="http://v8.1c.ru/8.3/xcf/enums" xmlns:xpr="http://v8.1c.ru/8.3/xcf/predef" xmlns:xr="http://v8.1c.ru/8.3/xcf/readable" xmlns:xs="http://www.w3.org/2001/XMLSchema" xmlns:xsi="http://www.w3.org/2001/XMLSchema-instance" version="2.10">
	<Constant uuid="649e37e0-c1fa-4b97-86ba-d6b92b1f24b5">
		<InternalInfo>
			<xr:GeneratedType name="ConstantManager.ИспользоватьПострочнуюОтгрузкуВЗаказеКлиента" category="Manager">
				<xr:TypeId>71ed7547-5760-4285-80f5-3ea3d9e72195</xr:TypeId>
				<xr:ValueId>00493612-363c-496a-be86-9f551180e455</xr:ValueId>
			</xr:GeneratedType>
			<xr:GeneratedType name="ConstantValueManager.ИспользоватьПострочнуюОтгрузкуВЗаказеКлиента" category="ValueManager">
				<xr:TypeId>244cc0e1-d8f0-473d-aa25-85d97a2df3ea</xr:TypeId>
				<xr:ValueId>0b91b60d-f396-4b8f-b9a4-54b62c9c5e1b</xr:ValueId>
			</xr:GeneratedType>
			<xr:GeneratedType name="ConstantValueKey.ИспользоватьПострочнуюОтгрузкуВЗаказеКлиента" category="ValueKey">
				<xr:TypeId>405b4bda-2038-4854-ad24-2b3d77a88f94</xr:TypeId>
				<xr:ValueId>19c8478c-a895-46b1-8b26-cbecfde340cb</xr:ValueId>
			</xr:GeneratedType>
		</InternalInfo>
		<Properties>
			<Name>ИспользоватьПострочнуюОтгрузкуВЗаказеКлиента</Name>
			<Comment/>
			<ObjectBelonging>Adopted</ObjectBelonging>
			<ExtendedConfigurationObject>71a5e47c-569d-49ab-9e82-ddf2a7fd542d</ExtendedConfigurationObject>
			<Type>
				<v8:Type>xs:boolean</v8:Type>
			</Type>
		</Properties>
	</Constant>
</MetaDataObject>